docs/source/conf.py
pyhelpers/__init__.py
pyhelpers/_cache.py
pyhelpers/data/.metadata
pyhelpers/data/ansi-escape-codes.json
pyhelpers/data/english-numerals.json
pyhelpers/data/optional-dependency.json
pyhelpers/data/user-agent-strings.json
pyhelpers/data/xlsx2csv.vbs
pyhelpers/dbms/__init__.py
pyhelpers/dbms/_base.py
pyhelpers/dbms/mssql.py
pyhelpers/dbms/postgresql.py
pyhelpers/dbms/utils.py
pyhelpers/dirs/__init__.py
pyhelpers/dirs/management.py
pyhelpers/dirs/navigation.py
pyhelpers/dirs/validation.py
pyhelpers/geom/__init__.py
pyhelpers/geom/distances.py
pyhelpers/geom/shapes.py
pyhelpers/geom/transforms.py
pyhelpers/ops/__init__.py
pyhelpers/ops/apis.py
pyhelpers/ops/computation.py
pyhelpers/ops/downloads.py
pyhelpers/ops/general.py
pyhelpers/ops/manipulation.py
pyhelpers/ops/web.py
pyhelpers/settings/__init__.py
pyhelpers/settings/configurations.py
pyhelpers/settings/preferences.py
pyhelpers/store/__init__.py
pyhelpers/store/converters.py
pyhelpers/store/loaders.py
pyhelpers/store/savers.py
pyhelpers/store/utils.py
pyhelpers/text/__init__.py
pyhelpers/text/preprocessing.py
pyhelpers/text/similarity.py
pyhelpers/viz/__init__.py
pyhelpers/viz/color_utils.py
pyhelpers/viz/colormap.py
pyhelpers-2.3.2.dist-info/licenses/LICENSE
pyhelpers-2.3.2.dist-info/METADATA
pyhelpers-2.3.2.dist-info/WHEEL
pyhelpers-2.3.2.dist-info/top_level.txt
pyhelpers-2.3.2.dist-info/RECORD
