Metadata-Version: 2.4
Name: pyhelpers
Version: 2.3.2
Summary: An open-source toolkit for facilitating Python users' data manipulation tasks
Home-page: https://github.com/mikeqfu/pyhelpers
Author: Qian Fu
Author-email: q.fu@bham.ac.uk
License: MIT
Project-URL: Documentation, https://pyhelpers.readthedocs.io/en/2.3.2/
Project-URL: Source, https://github.com/mikeqfu/pyhelpers
Project-URL: Bug Tracker, https://github.com/mikeqfu/pyhelpers/issues
Keywords: Python,Utilities,Data preprocessing,Data manipulation,Python utilities,Python utils,Python utility
Classifier: Intended Audience :: Developers
Classifier: Intended Audience :: Education
Classifier: Intended Audience :: Science/Research
Classifier: Topic :: Education
Classifier: Topic :: Scientific/Engineering
Classifier: Topic :: Software Development
Classifier: Topic :: Utilities
Classifier: Programming Language :: Python :: 3
Classifier: Operating System :: Microsoft :: Windows
Classifier: Operating System :: POSIX :: Linux
Requires-Python: >=3.12
License-File: LICENSE
Requires-Dist: numpy
Requires-Dist: pandas
Requires-Dist: psycopg2
Requires-Dist: pyproj
Requires-Dist: requests
Requires-Dist: shapely
Requires-Dist: sqlalchemy
Dynamic: author
Dynamic: author-email
Dynamic: home-page
Dynamic: license
Dynamic: license-file
Dynamic: project-url
Dynamic: summary
